[
null,
{"id":1,"atypeId":1,"description":"","etypeId":4,"traits":[],"iconIndex":161,"name":"Roupa do produtor","note":"","params":[0,0,0,0,0,0,0,0],"price":500},
{"id":2,"atypeId":2,"description":"","etypeId":4,"traits":[],"iconIndex":165,"name":"Roupa do empresário","note":"","params":[0,0,0,0,0,0,0,0],"price":1000},
{"id":3,"atypeId":3,"description":"","etypeId":4,"traits":[],"iconIndex":163,"name":"Roupa do empreendedor","note":"","params":[0,0,0,0,0,0,0,0],"price":2000},
{"id":4,"atypeId":4,"description":"","etypeId":4,"traits":[],"iconIndex":162,"name":"Roupa do magnata","note":"","params":[0,0,0,0,0,0,0,0],"price":5000}
]